Metadata-Version: 2.1
Name: vinnieshell
Version: 0.1.5
Summary: Vinnies Multi-Shell-Handler, a reverse shell handler that can handle multiple shells
Author: VilariStorms
Author-email: vilari@goatmail.uk
